Metadata-Version: 2.1
Name: streamlit_mic_recorder
Version: 0.0.7
Summary: Streamlit component that allows to record mono audio from the user's microphone, and/or perform speech recognition directly.
Home-page: https://github.com/B4PT0R/streamlit-mic-recorder
Author: Baptiste Ferrand
Author-email: bferrand.math@gmail.com
Requires-Python: >=3.7
License-File: LICENSE
Requires-Dist: streamlit >=0.63
Requires-Dist: SpeechRecognition
